odoo/addons/l10n_th_gov_purchase_agreement/README.rst
odoo/addons/l10n_th_gov_purchase_agreement/__init__.py
odoo/addons/l10n_th_gov_purchase_agreement/__manifest__.py
odoo/addons/l10n_th_gov_purchase_agreement/i18n/l10n_th_gov_purchase_agreement.pot
odoo/addons/l10n_th_gov_purchase_agreement/models/__init__.py
odoo/addons/l10n_th_gov_purchase_agreement/models/agreement.py
odoo/addons/l10n_th_gov_purchase_agreement/models/purchase.py
odoo/addons/l10n_th_gov_purchase_agreement/models/purchase_requisition.py
odoo/addons/l10n_th_gov_purchase_agreement/readme/CONTRIBUTORS.rst
odoo/addons/l10n_th_gov_purchase_agreement/readme/DESCRIPTION.rst
odoo/addons/l10n_th_gov_purchase_agreement/readme/USAGE.rst
odoo/addons/l10n_th_gov_purchase_agreement/static/description/icon.png
odoo/addons/l10n_th_gov_purchase_agreement/static/description/index.html
odoo/addons/l10n_th_gov_purchase_agreement/tests/__init__.py
odoo/addons/l10n_th_gov_purchase_agreement/tests/test_gov_purchase_agreement.py
odoo/addons/l10n_th_gov_purchase_agreement/views/agreement_views.xml
odoo/addons/l10n_th_gov_purchase_agreement/views/purchase_requisition_views.xml
odoo/addons/l10n_th_gov_purchase_agreement/views/purchase_views.xml
odoo14_addon_l10n_th_gov_purchase_agreement-14.0.1.0.1.dev3.dist-info/METADATA
odoo14_addon_l10n_th_gov_purchase_agreement-14.0.1.0.1.dev3.dist-info/WHEEL
odoo14_addon_l10n_th_gov_purchase_agreement-14.0.1.0.1.dev3.dist-info/top_level.txt
odoo14_addon_l10n_th_gov_purchase_agreement-14.0.1.0.1.dev3.dist-info/RECORD
