Metadata-Version: 2.1
Name: odoo14-addon-l10n-th-gov-purchase-agreement
Version: 14.0.1.0.1.dev3
Summary: Thai Localization - Government Purchase Agreement
Home-page: https://github.com/OCA/l10n-thailand
Author: Ecosoft, Odoo Community Association (OCA)
Author-email: support@odoo-community.org
License: AGPL-3
Platform: UNKNOWN
Classifier: Programming Language :: Python
Classifier: Framework :: Odoo
Classifier: Framework :: Odoo :: 14.0
Classifier: License :: OSI Approved :: GNU Affero General Public License v3
Classifier: Development Status :: 4 - Beta
Requires-Python: >=3.6
Requires-Dist: odoo14-addon-agreement-legal
Requires-Dist: odoo14-addon-purchase-invoice-plan
Requires-Dist: odoo <14.1dev,>=14.0a
